py3o.types-0.1.1-py3.4-nspkg.pth
py3o/types/__init__.py
py3o/types/config.py
py3o/types/json/__init__.py
py3o/types/json/decoder.py
py3o/types/json/encoder.py
py3o/types/types/__init__.py
py3o/types/types/base.py
py3o/types/types/date.py
py3o/types/types/dtime.py
py3o/types/types/float.py
py3o/types/types/integer.py
py3o/types/types/time.py
py3o.types-0.1.1.dist-info/DESCRIPTION.rst
py3o.types-0.1.1.dist-info/METADATA
py3o.types-0.1.1.dist-info/RECORD
py3o.types-0.1.1.dist-info/WHEEL
py3o.types-0.1.1.dist-info/entry_points.txt
py3o.types-0.1.1.dist-info/metadata.json
py3o.types-0.1.1.dist-info/namespace_packages.txt
py3o.types-0.1.1.dist-info/top_level.txt
py3o.types-0.1.1.dist-info/zip-safe
