Metadata-Version: 2.0
Name: py3o.types
Version: 0.1.1
Summary: Data type helpers for Py3o
Home-page: http://bitbucket.org/faide/py3o.types
Author: Jérémie Gavrel
Author-email: jeremie.gavrel@xcg-consulting.fr
License: MIT License
Keywords: LibreOffice OpenOffice templating PDF
Platform: UNKNOWN
Classifier: Programming Language :: Python
Classifier: Topic :: Software Development :: Libraries :: Python Modules
Classifier: Development Status :: 4 - Beta
Classifier: Intended Audience :: Developers
Classifier: License :: OSI Approved :: MIT License
Classifier: Operating System :: OS Independent
Requires-Dist: lxml
Requires-Dist: setuptools
Requires-Dist: six (>=1.4)
